memorious_mcp/__init__.py
memorious_mcp/backends/__init__.py
memorious_mcp/backends/chroma_backend.py
memorious_mcp/backends/memory_backend.py
memorious_mcp/main.py
memorious_mcp-0.0.2.dist-info/WHEEL
memorious_mcp-0.0.2.dist-info/entry_points.txt
memorious_mcp-0.0.2.dist-info/METADATA
memorious_mcp-0.0.2.dist-info/RECORD
