Metadata-Version: 2.3
Name: memorious-mcp
Version: 0.0.2
Summary: Persistent semantic key-value memory MCP server with ChromaDB backend
Author: Cedric Vidal
Author-email: Cedric Vidal <cedric.vidal@gmail.com>
License: MIT
Requires-Dist: chromadb>=1.0.21
Requires-Dist: mcp[cli]>=1.14.0
Requires-Dist: fastmcp>=2.0.0
Requires-Dist: pytest>=8.4.2
Requires-Dist: pytest>=7.0 ; extra == 'dev'
Requires-Dist: pyyaml>=6.0 ; extra == 'dev'
Requires-Python: >=3.12
Project-URL: Documentation, https://github.com/cedricvidal/memorious-mcp#readme
Project-URL: Issues, https://github.com/cedricvidal/memorious-mcp/issues
Project-URL: Source, https://github.com/cedricvidal/memorious-mcp
Provides-Extra: dev
